setup.py
wheelcms_carousel/__init__.py
wheelcms_carousel/models.py
wheelcms_carousel.egg-info/PKG-INFO
wheelcms_carousel.egg-info/SOURCES.txt
wheelcms_carousel.egg-info/dependency_links.txt
wheelcms_carousel.egg-info/namespace_packages.txt
wheelcms_carousel.egg-info/not-zip-safe
wheelcms_carousel.egg-info/requires.txt
wheelcms_carousel.egg-info/top_level.txt