Metadata-Version: 1.1
Name: wheelcms-carousel
Version: 1.1
Summary: WheelCMS frontpage carousel
Home-page: http://github.com/wheelcms/wheelcms_carousel
Author: Ivo van der Wijk
Author-email: wheelcms@in.m3r.nl
License: BSD
Platform: UNKNOWN
Classifier: Programming Language :: Python
